epidemix/__init__.py
epidemix/__main__.py
epidemix/epidemic.py
epidemix/equations.py
epidemix/macro.py
epidemix/vaccination.py
epidemix-1.1.2.dist-info/LICENSE.txt
epidemix-1.1.2.dist-info/METADATA
epidemix-1.1.2.dist-info/WHEEL
epidemix-1.1.2.dist-info/entry_points.txt
epidemix-1.1.2.dist-info/top_level.txt
epidemix-1.1.2.dist-info/RECORD
