Metadata-Version: 2.1
Name: epidemix
Version: 1.1.2
Summary: Simulation of Epidemic Propagation on a Network
Home-page: https://github.com/khle08/epidemix
Author: Guo Jun-Lin
Author-email: guojl19@mails.tsinghua.edu.cn
License: BSD-2-Clause
Keywords: epidemic,vaccination,graph,networkx,community,propagation,differential-equation,covid-19,cdlib
Platform: UNKNOWN
Classifier: Development Status :: 3 - Alpha
Classifier: Intended Audience :: Developers
Classifier: Topic :: Software Development :: Build Tools
Classifier: License :: OSI Approved :: BSD License
Classifier: Operating System :: OS Independent
Classifier: Programming Language :: Python :: 3
Requires-Dist: networkx
Requires-Dist: numpy
Requires-Dist: matplotlib
Requires-Dist: tqdm
Requires-Dist: scipy
Requires-Dist: cdlib
Requires-Dist: future
